Metadata-Version: 1.0
Name: akera-distribution
Version: 0.2
Summary: Gaussian and Binomial distributions
Home-page: UNKNOWN
Author: Salaudeen Hafeez
Author-email: amplifiedsalaudeenak21@gmail.com
License: UNKNOWN
Platform: UNKNOWN
